auth_framework/__init__.py
auth_framework/abstract_models.py
auth_framework/admin.py
auth_framework/apps.py
auth_framework/backends/__init__.py
auth_framework/backends/auth_backends.py
auth_framework/exceptions.py
auth_framework/migrations/0001_initial.py
auth_framework/migrations/__init__.py
auth_framework/models.py
auth_framework/oauth/__init__.py
auth_framework/oauth/oauth2_backends.py
auth_framework/oauth/oauth2_validators.py
auth_framework/oauth/serializers.py
auth_framework/oauth/urls.py
auth_framework/oauth/utils.py
auth_framework/oauth/views.py
auth_framework/permissions.py
auth_framework/serializers/__init__.py
auth_framework/serializers/account_serializers.py
auth_framework/serializers/mixin_serializers.py
auth_framework/serializers/password_serializers.py
auth_framework/serializers/signup_serializers.py
auth_framework/settings.py
auth_framework/signals/__init__.py
auth_framework/signals/handler.py
auth_framework/social/__init__.py
auth_framework/social/providers/__init__.py
auth_framework/social/providers/abstract_adapter.py
auth_framework/social/providers/apple/__init__.py
auth_framework/social/providers/apple/adapter.py
auth_framework/social/providers/facebook/__init__.py
auth_framework/social/providers/facebook/adapter.py
auth_framework/social/providers/google/__init__.py
auth_framework/social/providers/google/adapter.py
auth_framework/social/serializers.py
auth_framework/social/urls.py
auth_framework/social/views.py
auth_framework/tasks.py
auth_framework/templates/auth/email_pin.txt
auth_framework/templates/auth/email_reset_link.txt
auth_framework/urls.py
auth_framework/utils.py
auth_framework/views/__init__.py
auth_framework/views/account_views.py
auth_framework/views/password_views.py
auth_framework/views/session_views.py
django_auth_framework-2.0.7.dist-info/WHEEL
django_auth_framework-2.0.7.dist-info/METADATA
django_auth_framework-2.0.7.dist-info/license_files/LICENSE
django_auth_framework-2.0.7.dist-info/RECORD
