Metadata-Version: 2.1
Name: django-auth-framework
Version: 2.0.7
Summary: An open source, one-stop authentication framework for Django and ready for production.
License: BSD-2-Clause
Author-email: Edward Chai <edwardc@acrossor.com>
Requires-Python: >=3.8,<4.0
Classifier: Development Status :: 5 - Production/Stable
Classifier: Environment :: Web Environment
Classifier: Framework :: Django
Classifier: Framework :: Django :: 2.2
Classifier: Framework :: Django :: 3.1
Classifier: Framework :: Django :: 3.2
Classifier: Framework :: Django :: 4.0
Classifier: Intended Audience :: Developers
Classifier: License :: OSI Approved :: BSD License
Classifier: Operating System :: OS Independent
Classifier: Programming Language :: Python :: 3
Classifier: Programming Language :: Python :: 3.8
Classifier: Programming Language :: Python :: 3.9
Classifier: Topic :: Internet :: WWW/HTTP
Requires-Dist: django-oauth-toolkit<3.0.0,>=2.0.0
Requires-Dist: django>=3.2.0
Requires-Dist: djangorestframework<4,>=3
Requires-Dist: requests
Project-URL: homepage, https://github.com/DrChai/django-auth-framework
Project-URL: repository, https://github.com/DrChai/django-auth-framework
